MANIFEST.in
README.md
requirements.txt
setup.cfg
setup.py
versioneer.py
botcity/plugins/telegram/__init__.py
botcity/plugins/telegram/_version.py
botcity/plugins/telegram/plugin.py
botcity_telegram_plugin.egg-info/PKG-INFO
botcity_telegram_plugin.egg-info/SOURCES.txt
botcity_telegram_plugin.egg-info/dependency_links.txt
botcity_telegram_plugin.egg-info/requires.txt
botcity_telegram_plugin.egg-info/top_level.txt