Metadata-Version: 2.1
Name: botcity-telegram-plugin
Version: 0.1.3
Home-page: https://bitbucket.org/botcitydev/bot-telegram-plugin-python.git
Requires-Python: >=3.7
